SENTIMENT_LITE/__init__.py
SENTIMENT_LITE/core.py
sentiment_lite-0.1.0.dist-info/licenses/LICENSE
sentiment_lite-0.1.0.dist-info/METADATA
sentiment_lite-0.1.0.dist-info/WHEEL
sentiment_lite-0.1.0.dist-info/top_level.txt
sentiment_lite-0.1.0.dist-info/RECORD
