Metadata-Version: 2.4
Name: sentiment-lite
Version: 0.1.0
Summary: A simple lexicon-based sentiment analysis tool
Home-page: https://github.com/yourusername/sentiment-lite
Author: Divya Athalye
Author-email: divya.athalye@gmail.com
Classifier: Programming Language :: Python :: 3
Classifier: License :: OSI Approved :: MIT License
Classifier: Operating System :: OS Independent
Classifier: Topic :: Text Processing :: Linguistic
Requires-Python: >=3.6
License-File: LICENSE
Dynamic: author
Dynamic: author-email
Dynamic: classifier
Dynamic: description
Dynamic: description-content-type
Dynamic: home-page
Dynamic: license-file
Dynamic: requires-python
Dynamic: summary
